icalendar_light/__init__.py
icalendar_light/casters.py
icalendar_light/cli.py
icalendar_light/toolbox.py
icalendar_light-1.0.0.dist-info/AUTHORS
icalendar_light-1.0.0.dist-info/LICENSE
icalendar_light-1.0.0.dist-info/METADATA
icalendar_light-1.0.0.dist-info/WHEEL
icalendar_light-1.0.0.dist-info/entry_points.txt
icalendar_light-1.0.0.dist-info/top_level.txt
icalendar_light-1.0.0.dist-info/RECORD
