Metadata-Version: 2.1
Name: icalendar-light
Version: 1.0.0
Summary: Light and easy iCalendar event reader
Home-page: https://github.com/idlesign/icalendar_light
Author: Igor `idle sign` Starikov
Author-email: idlesign@yandex.ru
License: BSD 3-Clause License
Platform: UNKNOWN
Classifier: Development Status :: 5 - Production/Stable
Classifier: Operating System :: OS Independent
Classifier: Programming Language :: Python
Classifier: Programming Language :: Python :: 3
Classifier: Programming Language :: Python :: 3.6
Classifier: Programming Language :: Python :: 3.7
Classifier: Programming Language :: Python :: 3.8
Classifier: License :: OSI Approved :: BSD License
Requires-Dist: python-dateutil
Provides-Extra: cli
Requires-Dist: click ; extra == 'cli'
